{
  "member": [
    {
      "profileImage": "https://picsum.photos/200",
      "nickname": "홍길동",
      "mbti": "INFJ"
    }
  ],
  "place": [
    {
      "id": 1,
      "title": "인테리어가 아름다운 리빙형 대관 공간",
      "address": "경기도 남양주시",
      "image": "https://picsum.photos/201",
      "charge": 30000,
      "score": 4.8
    },
    {
      "id": 2,
      "title": "바다가 보이는 놀기좋은 곳",
      "address": "강원도 속초시",
      "image": "https://picsum.photos/202",
      "charge": 45000,
      "score": 3.2
    },
    {
      "id": 3,
      "title": "남산이 보이는 아늑한 숙소",
      "address": "서울특별시 용산구",
      "image": "https://picsum.photos/203",
      "charge": 106000,
      "score": 2.7
    }
  ],
  "reserve": [
    {
      "reserveId": 1,
      "placeId": 1,
      "title": "인테리어가 아름다운 리빙형 대관 공간",
      "address": "경기도 남양주시",
      "image": "https://picsum.photos/201",
      "startTime": "2022-11-18T02:00:00.000Z",
      "endTime": "2022-11-18T05:00:00.000Z",
      "totalCharge": 120000
    },
    {
      "reserveId": 2,
      "placeId": 2,
      "title": "바다가 보이는 놀기좋은 곳",
      "address": "강원도 속초시",
      "image": "https://picsum.photos/202",
      "startTime": "2022-11-20T10:00:00.000Z",
      "endTime": "2022-11-20T12:00:00.000Z",
      "totalCharge": 90000
    }
  ],
  "bookmark": [
    {
      "bookmarkId": 1,
      "placeId": 1,
      "image": "https://picsum.photos/202",
      "title": "바다가 보이는 놀기좋은 곳",
      "score": 3.2,
      "charge": 45000,
      "address": "강원도 속초시"
    },
    {
      "bookmarkId": 2,
      "placeId": 2,
      "image": "https://picsum.photos/201",
      "title": "인테리어가 아름다운 리빙형 대관 공간",
      "score": 4.8,
      "charge": 30000,
      "address": "경기도 남양주시"
    }
  ],
  "review": [
    {
      "id": 1,
      "placeId": 1,
      "title": "남산이 보이는 아늑한 숙소",
      "score": 2,
      "comment": "남산이 잘 안보였습니다.",
      "createdAt": "2022.11.08"
    },
    {
      "id": 2,
      "placeId": 2,
      "title": "인테리어가 아름다운 리빙형 대관 공간",
      "score": 4,
      "comment": "인테리어가 이쁘고 깨끗해요.",
      "createdAt": "2022.11.03"
    }
  ]
}
